yacman/__init__.py
yacman/_version.py
yacman/alias.py
yacman/const.py
yacman/exceptions.py
yacman/yacman.py
yacman/yacman1.py
yacman/yacman_future.py
yacman-0.9.3.dist-info/LICENSE.txt
yacman-0.9.3.dist-info/METADATA
yacman-0.9.3.dist-info/WHEEL
yacman-0.9.3.dist-info/top_level.txt
yacman-0.9.3.dist-info/RECORD
