Metadata-Version: 2.1
Name: yacman
Version: 0.9.3
Summary: A standardized configuration object for reference genome assemblies
Home-page: https://github.com/databio/yacman
Author: Nathan Sheffield, Michal Stolarczyk
Author-email: nathan@code.databio.org
License: BSD2
Keywords: bioinformatics,sequencing,ngs
Classifier: Development Status :: 4 - Beta
Classifier: License :: OSI Approved :: BSD License
Classifier: Programming Language :: Python :: 3.8
Classifier: Programming Language :: Python :: 3.9
Classifier: Programming Language :: Python :: 3.10
Classifier: Programming Language :: Python :: 3.11
Classifier: Programming Language :: Python :: 3.12
Classifier: Topic :: Scientific/Engineering :: Bio-Informatics
License-File: LICENSE.txt
Requires-Dist: attmap>=0.13.0
Requires-Dist: jsonschema>=3.2.0
Requires-Dist: oyaml
Requires-Dist: pyyaml>=3.13
Requires-Dist: ubiquerg>=0.7.0
